{
	"animations": [
		{
			"loop": false,
			"offsets": [
				-21,
				10
			],
			"anim": "idle",
			"fps": 19,
			"name": "Idle",
			"indices": []
		},
		{
			"loop": true,
			"offsets": [
				-31,
				0
			],
			"anim": "idle-loop",
			"fps": 19,
			"name": "Idle",
			"indices": []
		},
		{
			"loop": false,
			"offsets": [
				20,
				-130
			],
			"anim": "singDOWN",
			"fps": 23,
			"name": "Sing Down",
			"indices": []
		},
		{
			"loop": true,
			"offsets": [
				8,
				-130
			],
			"anim": "singDOWN-loop",
			"fps": 23,
			"name": "Sing Down",
			"indices": []
		},
		{
			"loop": false,
			"offsets": [
				240,
				-3
			],
			"anim": "singLEFT",
			"fps": 23,
			"name": "Sing Left",
			"indices": []
		},
		{
			"loop": true,
			"offsets": [
				240,
				0
			],
			"anim": "singLEFT-loop",
			"fps": 23,
			"name": "Sing Left",
			"indices": []
		},
		{
			"loop": false,
			"offsets": [
				-220,
				6
			],
			"anim": "singRIGHT",
			"fps": 23,
			"name": "Sing Right",
			"indices": []
		},
		{
			"loop": true,
			"offsets": [
				-224,
				0
			],
			"anim": "singRIGHT-loop",
			"fps": 23,
			"name": "Sing Right",
			"indices": []
		},
		{
			"loop": false,
			"offsets": [
				4,
				21
			],
			"anim": "singUP",
			"fps": 23,
			"name": "Sing Up",
			"indices": []
		},
		{
			"loop": true,
			"offsets": [
				-1,
				10
			],
			"anim": "singUP-loop",
			"fps": 23,
			"name": "Sing Up",
			"indices": []
		},
		{
			"loop": false,
			"offsets": [
				50,
				0
			],
			"anim": "hey",
			"fps": 22,
			"name": "Ugh",
			"indices": []
		}
	],
	"no_antialiasing": false,
	"image": "characters/ron",
	"position": [
		-30,
		230
	],
	"healthicon": "ron",
	"flip_x": false,
	"healthbar_colors": [
		255,
		255,
		0
	],
	"camera_position": [
		-110,
		80
	],
	"sing_duration": 4,
	"scale": 0.999999999999999
}